habitmove/__init__.py
habitmove/cli.py
habitmove/habits.py
habitmove/loopdata.py
habitmove/nomie.py
habitmove/nomiedata.py
habitmove/repetitions.py
habitmove/schema.py
habitmove-0.4.1.dist-info/entry_points.txt
habitmove-0.4.1.dist-info/WHEEL
habitmove-0.4.1.dist-info/METADATA
habitmove-0.4.1.dist-info/RECORD
