Metadata-Version: 2.1
Name: habitmove
Version: 0.4.1
Summary: migrate nomie data to loop habits tracker
Home-page: https://git.martyoeh.me/Marty/habit-migrate
License: GPL-3.0-only
Author: Marty Oehme
Author-email: marty.oehme@gmail.com
Requires-Python: >=3.7,<4.0
Classifier: License :: OSI Approved :: GNU General Public License v3 (GPLv3)
Classifier: Programming Language :: Python :: 3
Classifier: Programming Language :: Python :: 3.10
Classifier: Programming Language :: Python :: 3.7
Classifier: Programming Language :: Python :: 3.8
Classifier: Programming Language :: Python :: 3.9
Requires-Dist: click (>=8.0,<9.0)
Requires-Dist: importlib-metadata (>=0.23,<0.24); python_version < "3.8"
Project-URL: Repository, https://git.martyoeh.me/Marty/habit-migrate
